signalpilot_ai_internal/__init__.py
signalpilot_ai_internal/_version.py
signalpilot_ai_internal/cache_handlers.py
signalpilot_ai_internal/cache_service.py
signalpilot_ai_internal/composio_handlers.py
signalpilot_ai_internal/composio_service.py
signalpilot_ai_internal/database_config_handlers.py
signalpilot_ai_internal/database_config_service.py
signalpilot_ai_internal/databricks_schema_service.py
signalpilot_ai_internal/file_scanner_service.py
signalpilot_ai_internal/handlers.py
signalpilot_ai_internal/integrations_config.py
signalpilot_ai_internal/log_utils.py
signalpilot_ai_internal/mcp_handlers.py
signalpilot_ai_internal/mcp_server_manager.py
signalpilot_ai_internal/mcp_service.py
signalpilot_ai_internal/oauth_token_store.py
signalpilot_ai_internal/schema_search_config.yml
signalpilot_ai_internal/schema_search_service.py
signalpilot_ai_internal/signalpilot_home.py
signalpilot_ai_internal/snowflake_schema_service.py
signalpilot_ai_internal/test_dbt_mcp_server.py
signalpilot_ai_internal/unified_database_schema_service.py
signalpilot_ai_internal/html_export_template/README.md
signalpilot_ai_internal/html_export_template/conf.json
signalpilot_ai_internal/html_export_template/index.html.j2
signalpilot_ai_internal/tests/__init__.py
signalpilot_ai_internal/tests/test_handlers.py
signalpilot_ai_internal-0.11.15.data/data/etc/jupyter/jupyter_server_config.d/signalpilot_ai.json
signalpilot_ai_internal-0.11.15.data/data/share/jupyter/labextensions/signalpilot-ai-internal/package.json
signalpilot_ai_internal-0.11.15.data/data/share/jupyter/labextensions/signalpilot-ai-internal/schemas/signalpilot-ai-internal/package.json.orig
signalpilot_ai_internal-0.11.15.data/data/share/jupyter/labextensions/signalpilot-ai-internal/schemas/signalpilot-ai-internal/plugin.json
signalpilot_ai_internal-0.11.15.data/data/share/jupyter/labextensions/signalpilot-ai-internal/static/110.224e83db03814fd03955.js
signalpilot_ai_internal-0.11.15.dist-info/METADATA
signalpilot_ai_internal-0.11.15.dist-info/WHEEL
signalpilot_ai_internal-0.11.15.dist-info/licenses/LICENSE
signalpilot_ai_internal-0.11.15.dist-info/RECORD
