Metadata-Version: 2.4
Name: signalpilot_ai_internal
Version: 0.11.15
Summary: SignalPilot Agent - Your Jupyter Notebook Assistant
Project-URL: Homepage, https://signalpilot.ai/
Author-email: Daniel Schaffield <danielschaffield@gmail.com>
License: Copyright (c) 2025-2026 SignalPilot Inc. All rights reserved.
License-File: LICENSE
Keywords: jupyter,jupyterlab,jupyterlab-extension
Classifier: Framework :: Jupyter
Classifier: Framework :: Jupyter :: JupyterLab
Classifier: Framework :: Jupyter :: JupyterLab :: 4
Classifier: Framework :: Jupyter :: JupyterLab :: Extensions
Classifier: Framework :: Jupyter :: JupyterLab :: Extensions :: Prebuilt
Classifier: Intended Audience :: Developers
Classifier: Intended Audience :: Science/Research
Classifier: License :: Other/Proprietary License
Classifier: Programming Language :: Python
Classifier: Programming Language :: Python :: 3
Classifier: Programming Language :: Python :: 3.10
Classifier: Programming Language :: Python :: 3.11
Classifier: Programming Language :: Python :: 3.12
Classifier: Programming Language :: Python :: 3.13
Classifier: Programming Language :: Python :: 3.14
Classifier: Topic :: Scientific/Engineering
Classifier: Topic :: Software Development
Requires-Python: >=3.10
Requires-Dist: aiohttp>=3.9.0
Requires-Dist: jupyter-server<3,>=2.4.0
Requires-Dist: openpyxl
Requires-Dist: pandas>=2.0.0
Requires-Dist: pyarrow
Requires-Dist: schema-search[bigquery,databricks,mysql,postgres,snowflake]
Provides-Extra: test
Requires-Dist: coverage; extra == 'test'
Requires-Dist: pytest; extra == 'test'
Requires-Dist: pytest-asyncio; extra == 'test'
Requires-Dist: pytest-cov; extra == 'test'
Requires-Dist: pytest-jupyter[server]>=0.6.0; extra == 'test'
